mpr.py
rmpr.py
openmpr-1.0.dist-info/LICENSE
openmpr-1.0.dist-info/METADATA
openmpr-1.0.dist-info/WHEEL
openmpr-1.0.dist-info/top_level.txt
openmpr-1.0.dist-info/RECORD
